orbit_tessellation-0.2.0.dist-info/METADATA
orbit_tessellation-0.2.0.dist-info/WHEEL
tessellation/__init__.py
tessellation/base.py
tessellation/constructor.py
tessellation/dim2.py
tessellation/dim3.py
tessellation/exceptions.py
tessellation/generic.py
orbit_tessellation-0.2.0.dist-info/RECORD
