Metadata-Version: 2.1
Name: orbit-tessellation
Version: 0.2.0
Summary: A Python package for evaluating orbit commensurability using Delaunay tessellation.
Author-Email: ilikecubesnstuff <subho1618@gmail.com>
License: MIT
Classifier: Intended Audience :: Science/Research
Classifier: License :: OSI Approved :: MIT License
Classifier: Programming Language :: Python :: 3 :: Only
Classifier: Programming Language :: Python :: 3.9
Classifier: Programming Language :: Python :: 3.10
Classifier: Programming Language :: Python :: 3.11
Classifier: Programming Language :: Python :: 3.12
Classifier: Topic :: Scientific/Engineering :: Physics
Project-URL: Repository, https://github.com/ilikecubesnstuff/orbit-tessellation
Requires-Python: >=3.9
Requires-Dist: numpy>=1.24.4
Requires-Dist: scipy>=1.9.3
Requires-Dist: matplotlib>=3.7.2; extra == "plotting"
Provides-Extra: plotting
